LICENSE.txt
MANIFEST.in
README.rst
setup.cfg
setup.py
two_captcha_sdk.egg-info/PKG-INFO
two_captcha_sdk.egg-info/SOURCES.txt
two_captcha_sdk.egg-info/dependency_links.txt
two_captcha_sdk.egg-info/requires.txt
two_captcha_sdk.egg-info/top_level.txt
twocaptcha/__init__.py
twocaptcha/wrapper.py