Metadata-Version: 1.1
Name: two-captcha-sdk
Version: 0.0.2.1
Summary: 2Captcha Python3 API Wrapper
Home-page: https://github.com/kfichter/2captcha-py-sdk
Author: Kelvin Fichter
Author-email: UNKNOWN
License: MIT
Keywords: 2captcha development
Platform: UNKNOWN
Classifier: Development Status :: 3 - Alpha
Classifier: Intended Audience :: Developers
Classifier: Topic :: Software Development :: Libraries :: Python Modules
Classifier: License :: OSI Approved :: MIT License
Classifier: Programming Language :: Python :: 3.5
